wagtail_social_share/__init__.py
wagtail_social_share/apps.py
wagtail_social_share/edit_handlers.py
wagtail_social_share/exceptions.py
wagtail_social_share/mixins.py
wagtail_social_share/models.py
wagtail_social_share/settings.py
wagtail_social_share/sharer.py
wagtail_social_share/signals.py
wagtail_social_share/migrations/__init__.py
wagtail_social_share-0.1.4.dist-info/LICENSE
wagtail_social_share-0.1.4.dist-info/METADATA
wagtail_social_share-0.1.4.dist-info/WHEEL
wagtail_social_share-0.1.4.dist-info/top_level.txt
wagtail_social_share-0.1.4.dist-info/RECORD
