Metadata-Version: 2.1
Name: wagtail-social-share
Version: 0.1.4
Summary: Auto-share Wagtail Pages on Social Medias
Home-page: https://github.com/spamz23/wagtail-social-share
Author: Diogo Silva
Author-email: diogosilv30@gmail.com
License: MIT
Platform: UNKNOWN
Classifier: Programming Language :: Python :: 3
Classifier: License :: OSI Approved :: MIT License
Classifier: Operating System :: OS Independent
Requires-Python: >=3.6
License-File: LICENSE
Requires-Dist: wagtail (>2.0)
Requires-Dist: python-twitter (==3.5)
Requires-Dist: facebook-sdk (==3.1.0)
